pm_cedp_qdp/__init__.py
pm_cedp_qdp/qdp.py
pm_cedp_qdp/utilities.py
pm_cedp_qdp-0.1.2.dist-info/LICENSE
pm_cedp_qdp-0.1.2.dist-info/METADATA
pm_cedp_qdp-0.1.2.dist-info/WHEEL
pm_cedp_qdp-0.1.2.dist-info/top_level.txt
pm_cedp_qdp-0.1.2.dist-info/RECORD
