Metadata-Version: 2.1
Name: pm-cedp-qdp
Version: 0.1.2
Summary: Quantifying Temporal Privacy Leakage in Continuous Event Data Publishing
Home-page: https://github.com/m4jidRafiei/QDP_CEDP
Author: Majid Rafiei
Author-email: majid.rafiei@pads.rwth-aachen.de
License: UNKNOWN
Project-URL: Source, https://github.com/m4jidRafiei/QDP_CEDP
Platform: UNKNOWN
Classifier: Programming Language :: Python :: 3
Classifier: License :: OSI Approved :: GNU General Public License v3 (GPLv3)
Classifier: Operating System :: OS Independent
License-File: LICENSE
Requires-Dist: numpy (>=1.19.5)
Requires-Dist: pandas (>=1.1.5)
Requires-Dist: pm4py (>=2.2.15)
Requires-Dist: setuptools (>=59.6.0)
Requires-Dist: matplotlib (>=2.2.2)
